[
    {
        "text": "*[Shiwasu no Okina] Heisei Seikyouiku Kaikaku | Heisei Sexual Education Reform [Thai ภาษาไทย]*\nThai  -- Size: 31.44 MB (74 pages)\n<https:\/\/e-hentai.org\/g\/508585\/1d97102c72\/>",
        "username": "e-hentai.org",
        "bot_id": "B70KX4RRS",
        "mrkdwn": true,
        "attachments": [
            {
                "fallback": "*[Shiwasu no Okina] Heisei Seikyouiku Kaikaku | Heisei Sexual Education Reform [Thai ภาษาไทย]*\nThai  -- Size: 31.44 MB (74 pages)\n<https:\/\/e-hentai.org\/g\/508585\/1d97102c72\/>",
                "image_url": "https:\/\/ehgt.org\/t\/47\/9d\/479d1b054cdc33c0c153d3d71aa20d6740838813-411070-1143-1600-jpg_250.jpg",
                "image_width": 250,
                "image_height": 350,
                "image_bytes": 39589,
                "id": 1
            }
        ],
        "type": "message",
        "subtype": "bot_message",
        "ts": "1514285041.000026"
    },
    {
        "text": "*[Shiwasu no Okina] Heisei Seikyouiku Kaikaku | Heisei Sexual Education Reform [Thai ภาษาไทย]*\nThai  -- Size: 31.44 MB (74 pages)\n<https:\/\/e-hentai.org\/g\/508585\/1d97102c72\/>",
        "username": "e-hentai.org",
        "bot_id": "B70KX4RRS",
        "mrkdwn": true,
        "attachments": [
            {
                "fallback": "*[Shiwasu no Okina] Heisei Seikyouiku Kaikaku | Heisei Sexual Education Reform [Thai ภาษาไทย]*\nThai  -- Size: 31.44 MB (74 pages)\n<https:\/\/e-hentai.org\/g\/508585\/1d97102c72\/>",
                "image_url": "https:\/\/ehgt.org\/t\/47\/9d\/479d1b054cdc33c0c153d3d71aa20d6740838813-411070-1143-1600-jpg_250.jpg",
                "image_width": 250,
                "image_height": 350,
                "image_bytes": 39589,
                "id": 1
            }
        ],
        "type": "message",
        "subtype": "bot_message",
        "ts": "1514286680.000044"
    }
]