[
    {
        "text": "*My Hestia Cosplay Collection*\nJapanese  -- Size: 9.53 MB (77 pages)\n<https:\/\/e-hentai.org\/g\/1106912\/e10db2644e\/>",
        "username": "e-hentai.org",
        "bot_id": "B70KX4RRS",
        "mrkdwn": true,
        "attachments": [
            {
                "fallback": "*My Hestia Cosplay Collection*\nJapanese  -- Size: 9.53 MB (77 pages)\n<https:\/\/e-hentai.org\/g\/1106912\/e10db2644e\/>",
                "image_url": "https:\/\/ehgt.org\/t\/5e\/a5\/5ea5102f46243fc324091abbce219aa632e751cd-38838-639-960-jpg_250.jpg",
                "image_width": 250,
                "image_height": 375,
                "image_bytes": 17236,
                "id": 1
            }
        ],
        "type": "message",
        "subtype": "bot_message",
        "ts": "1510156966.000338"
    },
    {
        "text": "*[KURUPIKA] 監○学園２～濡れTシャツコンテスト～*\nJapanese  -- Size: 315.9 MB (260 pages)\n<https:\/\/e-hentai.org\/g\/914262\/937411cf89\/>",
        "username": "e-hentai.org",
        "bot_id": "B70KX4RRS",
        "mrkdwn": true,
        "attachments": [
            {
                "fallback": "*[KURUPIKA] 監○学園２～濡れTシャツコンテスト～*\nJapanese  -- Size: 315.9 MB (260 pages)\n<https:\/\/e-hentai.org\/g\/914262\/937411cf89\/>",
                "image_url": "https:\/\/ehgt.org\/t\/06\/ef\/06ef47b297d674a300c7bef4177248f5a3530c1f-1197142-1800-1200-jpg_250.jpg",
                "image_width": 250,
                "image_height": 167,
                "image_bytes": 11156,
                "id": 1
            }
        ],
        "type": "message",
        "subtype": "bot_message",
        "ts": "1510157659.000420"
    },
    {
        "text": "*nonsummerjack - The Lone Samurai -BAIKEN-*\nJapanese  -- Size: 172.6 MB (174 pages)\n<https:\/\/e-hentai.org\/g\/1069418\/a6c24cc347\/>",
        "username": "e-hentai.org",
        "bot_id": "B70KX4RRS",
        "mrkdwn": true,
        "attachments": [
            {
                "fallback": "*nonsummerjack - The Lone Samurai -BAIKEN-*\nJapanese  -- Size: 172.6 MB (174 pages)\n<https:\/\/e-hentai.org\/g\/1069418\/a6c24cc347\/>",
                "image_url": "https:\/\/ehgt.org\/t\/08\/2a\/082a266457fc8d1cc277fce6db27cedbd6a3d313-668832-1200-1800-jpg_250.jpg",
                "image_width": 250,
                "image_height": 375,
                "image_bytes": 18631,
                "id": 1
            }
        ],
        "type": "message",
        "subtype": "bot_message",
        "ts": "1510157930.000115"
    },
    {
        "text": "*[nonsummerjack (non)] 武蔵 －BATTLESHIP－*\nJapanese  -- Size: 232.2 MB (186 pages)\n<https:\/\/e-hentai.org\/g\/1087437\/9e724e6b15\/>",
        "username": "e-hentai.org",
        "bot_id": "B70KX4RRS",
        "mrkdwn": true,
        "attachments": [
            {
                "fallback": "*[nonsummerjack (non)] 武蔵 －BATTLESHIP－*\nJapanese  -- Size: 232.2 MB (186 pages)\n<https:\/\/e-hentai.org\/g\/1087437\/9e724e6b15\/>",
                "image_url": "https:\/\/ehgt.org\/t\/15\/e2\/15e2901b33e97c648ab1fbaac36cf0ee241ec974-612333-900-618-jpg_250.jpg",
                "image_width": 250,
                "image_height": 172,
                "image_bytes": 25395,
                "id": 1
            }
        ],
        "type": "message",
        "subtype": "bot_message",
        "ts": "1510157988.000304"
    },
    {
        "text": "*[nonsummerjack (non)] HUNTER+2ndG*\nJapanese  -- Size: 147.4 MB (175 pages)\n<https:\/\/e-hentai.org\/g\/1087428\/b240f1a9ab\/>",
        "username": "e-hentai.org",
        "bot_id": "B70KX4RRS",
        "mrkdwn": true,
        "attachments": [
            {
                "fallback": "*[nonsummerjack (non)] HUNTER+2ndG*\nJapanese  -- Size: 147.4 MB (175 pages)\n<https:\/\/e-hentai.org\/g\/1087428\/b240f1a9ab\/>",
                "image_url": "https:\/\/ehgt.org\/t\/63\/72\/637233b4f75007e86319a599eb04af4b976b774b-465948-800-550-jpg_250.jpg",
                "image_width": 250,
                "image_height": 172,
                "image_bytes": 22111,
                "id": 1
            }
        ],
        "type": "message",
        "subtype": "bot_message",
        "ts": "1510158009.000522"
    },
    {
        "text": "*[nonsummerjack (non)] GAL POLICE 24h*\nJapanese  -- Size: 406.5 MB (261 pages)\n<https:\/\/e-hentai.org\/g\/1085401\/d1298d2201\/>",
        "username": "e-hentai.org",
        "bot_id": "B70KX4RRS",
        "mrkdwn": true,
        "attachments": [
            {
                "fallback": "*[nonsummerjack (non)] GAL POLICE 24h*\nJapanese  -- Size: 406.5 MB (261 pages)\n<https:\/\/e-hentai.org\/g\/1085401\/d1298d2201\/>",
                "image_url": "https:\/\/ehgt.org\/t\/58\/5c\/585cb0169142ceb1545e608833f9cc3825a4dcac-500754-800-550-jpg_250.jpg",
                "image_width": 250,
                "image_height": 172,
                "image_bytes": 23983,
                "id": 1
            }
        ],
        "type": "message",
        "subtype": "bot_message",
        "ts": "1510158206.000039"
    },
    {
        "text": "*[nonsummerjack (non)] SIAM GOKORO*\nJapanese  -- Size: 285.1 MB (193 pages)\n<https:\/\/e-hentai.org\/g\/1084652\/bbf0db7388\/>",
        "username": "e-hentai.org",
        "bot_id": "B70KX4RRS",
        "mrkdwn": true,
        "attachments": [
            {
                "fallback": "*[nonsummerjack (non)] SIAM GOKORO*\nJapanese  -- Size: 285.1 MB (193 pages)\n<https:\/\/e-hentai.org\/g\/1084652\/bbf0db7388\/>",
                "image_url": "https:\/\/ehgt.org\/t\/33\/1b\/331b1b6e949d2126e6c6d24d70b6cb64a6528c3f-342866-560-385-jpg_250.jpg",
                "image_width": 250,
                "image_height": 172,
                "image_bytes": 28648,
                "id": 1
            }
        ],
        "type": "message",
        "subtype": "bot_message",
        "ts": "1510158225.000757"
    },
    {
        "text": "*[nonsummerjack (non)]My GOD ANUBIS*\nJapanese  -- Size: 234.5 MB (161 pages)\n<https:\/\/e-hentai.org\/g\/967766\/852a9c1d56\/>",
        "username": "e-hentai.org",
        "bot_id": "B70KX4RRS",
        "mrkdwn": true,
        "attachments": [
            {
                "fallback": "*[nonsummerjack (non)]My GOD ANUBIS*\nJapanese  -- Size: 234.5 MB (161 pages)\n<https:\/\/e-hentai.org\/g\/967766\/852a9c1d56\/>",
                "image_url": "https:\/\/ehgt.org\/t\/6a\/12\/6a12ac3009351661d747b793e1f879b0e8325156-175626-900-618-jpg_250.jpg",
                "image_width": 250,
                "image_height": 172,
                "image_bytes": 19133,
                "id": 1
            }
        ],
        "type": "message",
        "subtype": "bot_message",
        "ts": "1510158264.000147"
    },
    {
        "text": "*新婚計画㊙︎ファイル [Mikehouse]*\nJapanese  -- Size: 75.21 MB (119 pages)\n<https:\/\/e-hentai.org\/g\/1104402\/bc38cd48f7\/>",
        "username": "e-hentai.org",
        "bot_id": "B70KX4RRS",
        "mrkdwn": true,
        "attachments": [
            {
                "fallback": "*新婚計画㊙︎ファイル [Mikehouse]*\nJapanese  -- Size: 75.21 MB (119 pages)\n<https:\/\/e-hentai.org\/g\/1104402\/bc38cd48f7\/>",
                "image_url": "https:\/\/ehgt.org\/t\/f1\/26\/f126a4ea502aeed1af2b13019ab340c324905f3d-551036-1200-1800-jpg_250.jpg",
                "image_width": 250,
                "image_height": 375,
                "image_bytes": 16762,
                "id": 1
            }
        ],
        "type": "message",
        "subtype": "bot_message",
        "ts": "1510159012.000009"
    },
    {
        "text": "*(C89) [Shooting Star&amp;#039;s (Saku)] Body Blow (Kangoku Gakuen)*\nJapanese  -- Size: 105.8 MB (355 pages)\n<https:\/\/e-hentai.org\/g\/907494\/a5388af876\/>",
        "username": "e-hentai.org",
        "bot_id": "B70KX4RRS",
        "mrkdwn": true,
        "attachments": [
            {
                "fallback": "*(C89) [Shooting Star&amp;#039;s (Saku)] Body Blow (Kangoku Gakuen)*\nJapanese  -- Size: 105.8 MB (355 pages)\n<https:\/\/e-hentai.org\/g\/907494\/a5388af876\/>",
                "image_url": "https:\/\/ehgt.org\/t\/57\/21\/572197fec075c53fa508983edc0bdf2bbcfe846f-315345-1600-2400-jpg_250.jpg",
                "image_width": 250,
                "image_height": 375,
                "image_bytes": 21109,
                "id": 1
            }
        ],
        "type": "message",
        "subtype": "bot_message",
        "ts": "1510159842.000591"
    },
    {
        "text": "*[Shooting Star&amp;#039;s(saku)] mayoiga*\nJapanese  -- Size: 121.4 MB (267 pages)\n<https:\/\/e-hentai.org\/g\/901230\/08f892a054\/>",
        "username": "e-hentai.org",
        "bot_id": "B70KX4RRS",
        "mrkdwn": true,
        "attachments": [
            {
                "fallback": "*[Shooting Star&amp;#039;s(saku)] mayoiga*\nJapanese  -- Size: 121.4 MB (267 pages)\n<https:\/\/e-hentai.org\/g\/901230\/08f892a054\/>",
                "image_url": "https:\/\/ehgt.org\/t\/54\/ad\/54ad6a88b06f47c2d39c2021912baabc56c1635e-305301-1600-2400-jpg_250.jpg",
                "image_width": 250,
                "image_height": 375,
                "image_bytes": 24887,
                "id": 1
            }
        ],
        "type": "message",
        "subtype": "bot_message",
        "ts": "1510159886.000386"
    },
    {
        "text": "*(C89)[Shooting Star&amp;#039;s (Saku)] hatukoi (KanColle)*\nJapanese  -- Size: 52.28 MB (120 pages)\n<https:\/\/e-hentai.org\/g\/1044622\/8ac86c54bc\/>",
        "username": "e-hentai.org",
        "bot_id": "B70KX4RRS",
        "mrkdwn": true,
        "attachments": [
            {
                "fallback": "*(C89)[Shooting Star&amp;#039;s (Saku)] hatukoi (KanColle)*\nJapanese  -- Size: 52.28 MB (120 pages)\n<https:\/\/e-hentai.org\/g\/1044622\/8ac86c54bc\/>",
                "image_url": "https:\/\/ehgt.org\/t\/d7\/5c\/d75c8d5c6441fb0db85d2d757a4556f76e912807-585518-1597-2400-jpg_250.jpg",
                "image_width": 250,
                "image_height": 375,
                "image_bytes": 33974,
                "id": 1
            }
        ],
        "type": "message",
        "subtype": "bot_message",
        "ts": "1510159900.000336"
    },
    {
        "text": "*Shooting Star&amp;#039;s (Saku) ＬＯＶＥ　ＲＥＳＥＴ Rezero Emilia Tan \/ Rem \/ Rum*\nJapanese  -- Size: 112.4 MB (307 pages)\n<https:\/\/e-hentai.org\/g\/1067539\/5dc851b306\/>",
        "username": "e-hentai.org",
        "bot_id": "B70KX4RRS",
        "mrkdwn": true,
        "attachments": [
            {
                "fallback": "*Shooting Star&amp;#039;s (Saku) ＬＯＶＥ　ＲＥＳＥＴ Rezero Emilia Tan \/ Rem \/ Rum*\nJapanese  -- Size: 112.4 MB (307 pages)\n<https:\/\/e-hentai.org\/g\/1067539\/5dc851b306\/>",
                "image_url": "https:\/\/ehgt.org\/t\/85\/16\/851632bcd9c2517c8f8efd99edb2e4e7937cc3a7-642464-1600-2400-jpg_250.jpg",
                "image_width": 250,
                "image_height": 375,
                "image_bytes": 29962,
                "id": 1
            }
        ],
        "type": "message",
        "subtype": "bot_message",
        "ts": "1510159946.000031"
    },
    {
        "text": "*Coser Hoshilily (这很迟迟) [BCY@19413] (2017-04-23)*\nJapanese  -- Size: 845.3 MB (1458 pages)\n<https:\/\/e-hentai.org\/g\/1054659\/bedabc7cb8\/>",
        "username": "e-hentai.org",
        "bot_id": "B70KX4RRS",
        "mrkdwn": true,
        "attachments": [
            {
                "fallback": "*Coser Hoshilily (这很迟迟) [BCY@19413] (2017-04-23)*\nJapanese  -- Size: 845.3 MB (1458 pages)\n<https:\/\/e-hentai.org\/g\/1054659\/bedabc7cb8\/>",
                "image_url": "https:\/\/ehgt.org\/t\/b5\/69\/b56926e41a238793d7c40941e41e91adc77ac829-328494-601-900-jpg_250.jpg",
                "image_width": 250,
                "image_height": 374,
                "image_bytes": 25663,
                "id": 1
            }
        ],
        "type": "message",
        "subtype": "bot_message",
        "ts": "1510167827.000418"
    },
    {
        "text": "*ecchi wallpapers*\nJapanese  -- Size: 118.7 MB (125 pages)\n<https:\/\/e-hentai.org\/g\/1086065\/675aa225d3\/>",
        "username": "e-hentai.org",
        "bot_id": "B70KX4RRS",
        "mrkdwn": true,
        "attachments": [
            {
                "fallback": "*ecchi wallpapers*\nJapanese  -- Size: 118.7 MB (125 pages)\n<https:\/\/e-hentai.org\/g\/1086065\/675aa225d3\/>",
                "image_url": "https:\/\/ehgt.org\/t\/d7\/82\/d78247740f3faebfb9ad9c34e1afeb8c94e56258-2126042-1920-1080-jpg_250.jpg",
                "image_width": 250,
                "image_height": 141,
                "image_bytes": 20129,
                "id": 1
            }
        ],
        "type": "message",
        "subtype": "bot_message",
        "ts": "1510185706.000252"
    },
    {
        "text": "*[Pion Kim] various cosplay collection*\nJapanese  -- Size: 25.17 MB (105 pages)\n<https:\/\/e-hentai.org\/g\/1076302\/ac65bc9447\/>",
        "username": "e-hentai.org",
        "bot_id": "B70KX4RRS",
        "mrkdwn": true,
        "attachments": [
            {
                "fallback": "*[Pion Kim] various cosplay collection*\nJapanese  -- Size: 25.17 MB (105 pages)\n<https:\/\/e-hentai.org\/g\/1076302\/ac65bc9447\/>",
                "image_url": "https:\/\/ehgt.org\/t\/bb\/59\/bb593228cd53581086cb2cf33e46c4bf105919a4-368772-2048-1536-jpg_250.jpg",
                "image_width": 250,
                "image_height": 188,
                "image_bytes": 20424,
                "id": 1
            }
        ],
        "type": "message",
        "subtype": "bot_message",
        "ts": "1510185738.000199"
    },
    {
        "text": "*Coser Rollrollろろ (寒小肉肉Rollroll)*\nJapanese  -- Size: 223.6 MB (276 pages)\n<https:\/\/e-hentai.org\/g\/1066027\/015befb2e2\/>",
        "username": "e-hentai.org",
        "bot_id": "B70KX4RRS",
        "mrkdwn": true,
        "attachments": [
            {
                "fallback": "*Coser Rollrollろろ (寒小肉肉Rollroll)*\nJapanese  -- Size: 223.6 MB (276 pages)\n<https:\/\/e-hentai.org\/g\/1066027\/015befb2e2\/>",
                "image_url": "https:\/\/ehgt.org\/t\/77\/7c\/777c94c2048b8eacc0a3d3818bf7513db6a60e06-1024914-1200-1798-jpg_250.jpg",
                "image_width": 250,
                "image_height": 375,
                "image_bytes": 15413,
                "id": 1
            }
        ],
        "type": "message",
        "subtype": "bot_message",
        "ts": "1510185754.000139"
    },
    {
        "text": "*Coser SesshuAsuak (半半子) [BCY@33957] (2017-04-29)*\nJapanese  -- Size: 838.6 MB (523 pages)\n<https:\/\/e-hentai.org\/g\/1056796\/92bcb8cbb4\/>",
        "username": "e-hentai.org",
        "bot_id": "B70KX4RRS",
        "mrkdwn": true,
        "attachments": [
            {
                "fallback": "*Coser SesshuAsuak (半半子) [BCY@33957] (2017-04-29)*\nJapanese  -- Size: 838.6 MB (523 pages)\n<https:\/\/e-hentai.org\/g\/1056796\/92bcb8cbb4\/>",
                "image_url": "https:\/\/ehgt.org\/t\/9b\/44\/9b4462d5992458f828619116b407b78d959c5572-1997963-1668-2500-jpg_250.jpg",
                "image_width": 250,
                "image_height": 375,
                "image_bytes": 28458,
                "id": 1
            }
        ],
        "type": "message",
        "subtype": "bot_message",
        "ts": "1510185773.000160"
    },
    {
        "text": "*Coser Hoshilily (这很迟迟) [BCY@19413] (2017-04-23)*\nJapanese  -- Size: 845.3 MB (1458 pages)\n<https:\/\/e-hentai.org\/g\/1054659\/bedabc7cb8\/>",
        "username": "e-hentai.org",
        "bot_id": "B70KX4RRS",
        "mrkdwn": true,
        "attachments": [
            {
                "fallback": "*Coser Hoshilily (这很迟迟) [BCY@19413] (2017-04-23)*\nJapanese  -- Size: 845.3 MB (1458 pages)\n<https:\/\/e-hentai.org\/g\/1054659\/bedabc7cb8\/>",
                "image_url": "https:\/\/ehgt.org\/t\/b5\/69\/b56926e41a238793d7c40941e41e91adc77ac829-328494-601-900-jpg_250.jpg",
                "image_width": 250,
                "image_height": 374,
                "image_bytes": 25663,
                "id": 1
            }
        ],
        "type": "message",
        "subtype": "bot_message",
        "ts": "1510186145.000266"
    },
    {
        "text": "*(C82) [Final Dearest (Kibashii)] Toaru Kibashi no Kanzaki Kaori (Toaru Majutsu no Index)(Complete-Hq)*\nJapanese  -- Size: 368.8 MB (574 pages)\n<https:\/\/e-hentai.org\/g\/681228\/0d06612e17\/>",
        "username": "e-hentai.org",
        "bot_id": "B70KX4RRS",
        "mrkdwn": true,
        "attachments": [
            {
                "fallback": "*(C82) [Final Dearest (Kibashii)] Toaru Kibashi no Kanzaki Kaori (Toaru Majutsu no Index)(Complete-Hq)*\nJapanese  -- Size: 368.8 MB (574 pages)\n<https:\/\/e-hentai.org\/g\/681228\/0d06612e17\/>",
                "image_url": "https:\/\/ehgt.org\/t\/78\/5f\/785f3eb2d51bbe7cd77541f95769dccc99a2fb42-410420-1700-2556-jpg_250.jpg",
                "image_width": 249,
                "image_height": 375,
                "image_bytes": 14524,
                "id": 1
            }
        ],
        "type": "message",
        "subtype": "bot_message",
        "ts": "1510187274.000031"
    },
    {
        "text": "*(C80) [FINAL DEAREST (Kibashii)] Boku ga Kanu wo XX Shita Ano Hi (Ikkitousen)*\nJapanese  -- Size: 62.06 MB (120 pages)\n<https:\/\/e-hentai.org\/g\/635005\/0c007bdea6\/>",
        "username": "e-hentai.org",
        "bot_id": "B70KX4RRS",
        "mrkdwn": true,
        "attachments": [
            {
                "fallback": "*(C80) [FINAL DEAREST (Kibashii)] Boku ga Kanu wo XX Shita Ano Hi (Ikkitousen)*\nJapanese  -- Size: 62.06 MB (120 pages)\n<https:\/\/e-hentai.org\/g\/635005\/0c007bdea6\/>",
                "image_url": "https:\/\/ehgt.org\/t\/7e\/db\/7edb47956b6d94e2b5f9eb6cdb87fe14831eab65-572557-800-1200-jpg_250.jpg",
                "image_width": 250,
                "image_height": 375,
                "image_bytes": 16871,
                "id": 1
            }
        ],
        "type": "message",
        "subtype": "bot_message",
        "ts": "1510187438.000228"
    },
    {
        "text": "*(C80) [FINAL DEAREST (Kibashii)] Boku ga Kanu wo XX Shita Ano Hi (Ikkitousen)*\nJapanese  -- Size: 151.5 MB (174 pages)\n<https:\/\/e-hentai.org\/g\/635003\/be870eebe1\/>",
        "username": "e-hentai.org",
        "bot_id": "B70KX4RRS",
        "mrkdwn": true,
        "attachments": [
            {
                "fallback": "*(C80) [FINAL DEAREST (Kibashii)] Boku ga Kanu wo XX Shita Ano Hi (Ikkitousen)*\nJapanese  -- Size: 151.5 MB (174 pages)\n<https:\/\/e-hentai.org\/g\/635003\/be870eebe1\/>",
                "image_url": "https:\/\/ehgt.org\/t\/b4\/3a\/b43ac8b75f3e6ece63dc026f7395ff70bf744649-893672-1008-1512-jpg_250.jpg",
                "image_width": 250,
                "image_height": 375,
                "image_bytes": 19293,
                "id": 1
            }
        ],
        "type": "message",
        "subtype": "bot_message",
        "ts": "1510187451.000250"
    },
    {
        "text": "*coser:kibashi*\nJapanese  -- Size: 10.97 MB (47 pages)\n<https:\/\/e-hentai.org\/g\/538197\/d7a9fd6dd0\/>",
        "username": "e-hentai.org",
        "bot_id": "B70KX4RRS",
        "mrkdwn": true,
        "attachments": [
            {
                "fallback": "*coser:kibashi*\nJapanese  -- Size: 10.97 MB (47 pages)\n<https:\/\/e-hentai.org\/g\/538197\/d7a9fd6dd0\/>",
                "image_url": "https:\/\/ehgt.org\/t\/79\/ea\/79ea3e8e479b67805ad4895fc7fc44e9147a5004-90321-584-878-jpg_250.jpg",
                "image_width": 249,
                "image_height": 375,
                "image_bytes": 19640,
                "id": 1
            }
        ],
        "type": "message",
        "subtype": "bot_message",
        "ts": "1510187462.000139"
    },
    {
        "text": "*ibashi ~*\nJapanese  -- Size: 84.12 MB (234 pages)\n<https:\/\/e-hentai.org\/g\/635434\/a2453a2dc5\/>",
        "username": "e-hentai.org",
        "bot_id": "B70KX4RRS",
        "mrkdwn": true,
        "attachments": [
            {
                "fallback": "*ibashi ~*\nJapanese  -- Size: 84.12 MB (234 pages)\n<https:\/\/e-hentai.org\/g\/635434\/a2453a2dc5\/>",
                "image_url": "https:\/\/ehgt.org\/t\/71\/c0\/71c06073dc9393a131777b2fbb040cd0d3c5199e-92874-500-333-jpg_250.jpg",
                "image_width": 250,
                "image_height": 167,
                "image_bytes": 10307,
                "id": 1
            }
        ],
        "type": "message",
        "subtype": "bot_message",
        "ts": "1510187474.000198"
    },
    {
        "text": "*(C82) [FINAL DEAREST (Kibashii)] Tenjoutenge Yuigadokuson Kanzenmuketsu Ryofu Housen (Ikkitousen)*\nJapanese  -- Size: 211.5 MB (141 pages)\n<https:\/\/e-hentai.org\/g\/641888\/9af56a2853\/>",
        "username": "e-hentai.org",
        "bot_id": "B70KX4RRS",
        "mrkdwn": true,
        "attachments": [
            {
                "fallback": "*(C82) [FINAL DEAREST (Kibashii)] Tenjoutenge Yuigadokuson Kanzenmuketsu Ryofu Housen (Ikkitousen)*\nJapanese  -- Size: 211.5 MB (141 pages)\n<https:\/\/e-hentai.org\/g\/641888\/9af56a2853\/>",
                "image_url": "https:\/\/ehgt.org\/t\/90\/fd\/90fdc6c9171aa5fab4debe763f52d796dc3ea707-617825-2550-1700-jpg_250.jpg",
                "image_width": 250,
                "image_height": 167,
                "image_bytes": 10239,
                "id": 1
            }
        ],
        "type": "message",
        "subtype": "bot_message",
        "ts": "1510187485.000154"
    },
    {
        "text": "*(C83) [FINAL DEAREST (Kibashii)] Sentouki (Ikkitousen)*\nJapanese  -- Size: 204.3 MB (120 pages)\n<https:\/\/e-hentai.org\/g\/635613\/8e18dfd092\/>",
        "username": "e-hentai.org",
        "bot_id": "B70KX4RRS",
        "mrkdwn": true,
        "attachments": [
            {
                "fallback": "*(C83) [FINAL DEAREST (Kibashii)] Sentouki (Ikkitousen)*\nJapanese  -- Size: 204.3 MB (120 pages)\n<https:\/\/e-hentai.org\/g\/635613\/8e18dfd092\/>",
                "image_url": "https:\/\/ehgt.org\/t\/a6\/d6\/a6d6aa8f28b5134320dc10c7ad89a8ac3b2100e7-1799681-1500-2250-jpg_250.jpg",
                "image_width": 250,
                "image_height": 375,
                "image_bytes": 16124,
                "id": 1
            }
        ],
        "type": "message",
        "subtype": "bot_message",
        "ts": "1510187493.000133"
    },
    {
        "text": "*(C83) [FINAL DEAREST (Kibashii)] Sentouki (Ikkitousen)*\nJapanese  -- Size: 241.5 MB (132 pages)\n<https:\/\/e-hentai.org\/g\/636921\/2efc911631\/>",
        "username": "e-hentai.org",
        "bot_id": "B70KX4RRS",
        "mrkdwn": true,
        "attachments": [
            {
                "fallback": "*(C83) [FINAL DEAREST (Kibashii)] Sentouki (Ikkitousen)*\nJapanese  -- Size: 241.5 MB (132 pages)\n<https:\/\/e-hentai.org\/g\/636921\/2efc911631\/>",
                "image_url": "https:\/\/ehgt.org\/t\/4b\/b9\/4bb948697b151edeaf1c19287deb775ff7c6d718-1805948-1500-2254-jpg_250.jpg",
                "image_width": 250,
                "image_height": 375,
                "image_bytes": 20458,
                "id": 1
            }
        ],
        "type": "message",
        "subtype": "bot_message",
        "ts": "1510187503.000284"
    },
    {
        "text": "*(C82) [FINAL DEAREST (Kibashii)] Tenjoutenge Yuigadokuson Kanzenmuketsu Ryofu Housen (Ikkitousen)*\nJapanese  -- Size: 147.1 MB (56 pages)\n<https:\/\/e-hentai.org\/g\/636922\/b0c0856106\/>",
        "username": "e-hentai.org",
        "bot_id": "B70KX4RRS",
        "mrkdwn": true,
        "attachments": [
            {
                "fallback": "*(C82) [FINAL DEAREST (Kibashii)] Tenjoutenge Yuigadokuson Kanzenmuketsu Ryofu Housen (Ikkitousen)*\nJapanese  -- Size: 147.1 MB (56 pages)\n<https:\/\/e-hentai.org\/g\/636922\/b0c0856106\/>",
                "image_url": "https:\/\/ehgt.org\/t\/6f\/a8\/6fa8e630ebd1dc62f6995f6dd4bf180524122332-2896180-1700-2550-jpg_250.jpg",
                "image_width": 250,
                "image_height": 375,
                "image_bytes": 20000,
                "id": 1
            }
        ],
        "type": "message",
        "subtype": "bot_message",
        "ts": "1510187519.000390"
    },
    {
        "text": "*(C82) [FINAL DEAREST (Kibashii)] Tenjoutenge Yuigadokuson Kanzenmuketsu Ryofu Housen (Ikkitousen)*\nJapanese  -- Size: 218.6 MB (86 pages)\n<https:\/\/e-hentai.org\/g\/643447\/d1885efe92\/>",
        "username": "e-hentai.org",
        "bot_id": "B70KX4RRS",
        "mrkdwn": true,
        "attachments": [
            {
                "fallback": "*(C82) [FINAL DEAREST (Kibashii)] Tenjoutenge Yuigadokuson Kanzenmuketsu Ryofu Housen (Ikkitousen)*\nJapanese  -- Size: 218.6 MB (86 pages)\n<https:\/\/e-hentai.org\/g\/643447\/d1885efe92\/>",
                "image_url": "https:\/\/ehgt.org\/t\/f2\/93\/f2930db224c335dbf08710c3bfca8663d0bc5731-3258743-1700-2550-jpg_250.jpg",
                "image_width": 250,
                "image_height": 375,
                "image_bytes": 18567,
                "id": 1
            }
        ],
        "type": "message",
        "subtype": "bot_message",
        "ts": "1510187527.000237"
    },
    {
        "text": "*(C80) [FINAL DEAREST (Kibashii)] Boku to Ryomou ga XX Shita Ano Hi (Ikkitousen)*\nJapanese  -- Size: 162.0 MB (199 pages)\n<https:\/\/e-hentai.org\/g\/643708\/4025b877a8\/>",
        "username": "e-hentai.org",
        "bot_id": "B70KX4RRS",
        "mrkdwn": true,
        "attachments": [
            {
                "fallback": "*(C80) [FINAL DEAREST (Kibashii)] Boku to Ryomou ga XX Shita Ano Hi (Ikkitousen)*\nJapanese  -- Size: 162.0 MB (199 pages)\n<https:\/\/e-hentai.org\/g\/643708\/4025b877a8\/>",
                "image_url": "https:\/\/ehgt.org\/t\/43\/a7\/43a7c90df2a5b6b537ba7cdd87cf1d3d31319b27-767498-1021-1536-jpg_250.jpg",
                "image_width": 249,
                "image_height": 375,
                "image_bytes": 15797,
                "id": 1
            }
        ],
        "type": "message",
        "subtype": "bot_message",
        "ts": "1510187535.000220"
    },
    {
        "text": "*(C80) [FINAL DEAREST (Kibashii)] Boku to Ryomou ga XX Shita Ano Hi (Ikkitousen)*\nJapanese  -- Size: 57.02 MB (119 pages)\n<https:\/\/e-hentai.org\/g\/643711\/156070a77f\/>",
        "username": "e-hentai.org",
        "bot_id": "B70KX4RRS",
        "mrkdwn": true,
        "attachments": [
            {
                "fallback": "*(C80) [FINAL DEAREST (Kibashii)] Boku to Ryomou ga XX Shita Ano Hi (Ikkitousen)*\nJapanese  -- Size: 57.02 MB (119 pages)\n<https:\/\/e-hentai.org\/g\/643711\/156070a77f\/>",
                "image_url": "https:\/\/ehgt.org\/t\/df\/66\/df6629e1fbc6921b06a5ac88cd986a68d36c3589-609457-801-1204-jpg_250.jpg",
                "image_width": 249,
                "image_height": 375,
                "image_bytes": 19453,
                "id": 1
            }
        ],
        "type": "message",
        "subtype": "bot_message",
        "ts": "1510187544.000107"
    },
    {
        "text": "*(COSHOLIC 2) [FINAL DEAREST (Kibashii)] Mou-chan wa Ore no Yome! (Ikkitousen)*\nJapanese  -- Size: 120.0 MB (66 pages)\n<https:\/\/e-hentai.org\/g\/643717\/766bea2e38\/>",
        "username": "e-hentai.org",
        "bot_id": "B70KX4RRS",
        "mrkdwn": true,
        "attachments": [
            {
                "fallback": "*(COSHOLIC 2) [FINAL DEAREST (Kibashii)] Mou-chan wa Ore no Yome! (Ikkitousen)*\nJapanese  -- Size: 120.0 MB (66 pages)\n<https:\/\/e-hentai.org\/g\/643717\/766bea2e38\/>",
                "image_url": "https:\/\/ehgt.org\/t\/b0\/7a\/b07a75c9a1f8a68530087abedfe158d01a64d5d2-1578188-1533-2304-jpg_250.jpg",
                "image_width": 250,
                "image_height": 375,
                "image_bytes": 17369,
                "id": 1
            }
        ],
        "type": "message",
        "subtype": "bot_message",
        "ts": "1510187551.000032"
    },
    {
        "text": "*(COSHOLIC 2) [FINAL DEAREST (Kibashii)] Mou-chan wa Ore no Yome! (Ikkitousen)*\nJapanese  -- Size: 162.1 MB (90 pages)\n<https:\/\/e-hentai.org\/g\/643715\/3f427c873b\/>",
        "username": "e-hentai.org",
        "bot_id": "B70KX4RRS",
        "mrkdwn": true,
        "attachments": [
            {
                "fallback": "*(COSHOLIC 2) [FINAL DEAREST (Kibashii)] Mou-chan wa Ore no Yome! (Ikkitousen)*\nJapanese  -- Size: 162.1 MB (90 pages)\n<https:\/\/e-hentai.org\/g\/643715\/3f427c873b\/>",
                "image_url": "https:\/\/ehgt.org\/t\/ff\/42\/ff424c7ad1699ee0da635df9ee928ae014b6c7ad-1470341-1426-2130-jpg_250.jpg",
                "image_width": 250,
                "image_height": 373,
                "image_bytes": 16507,
                "id": 1
            }
        ],
        "type": "message",
        "subtype": "bot_message",
        "ts": "1510187559.000392"
    },
    {
        "text": "*(COSHOLIC 2) [FINAL DEAREST (Kibashii)] Mou-chan wa Ore no Yome! (Ikkitousen)*\nJapanese  -- Size: 110.8 MB (67 pages)\n<https:\/\/e-hentai.org\/g\/643713\/db959e5935\/>",
        "username": "e-hentai.org",
        "bot_id": "B70KX4RRS",
        "mrkdwn": true,
        "attachments": [
            {
                "fallback": "*(COSHOLIC 2) [FINAL DEAREST (Kibashii)] Mou-chan wa Ore no Yome! (Ikkitousen)*\nJapanese  -- Size: 110.8 MB (67 pages)\n<https:\/\/e-hentai.org\/g\/643713\/db959e5935\/>",
                "image_url": "https:\/\/ehgt.org\/t\/8f\/36\/8f36208b3a5ae957d4c7e29b8dbb9aad7843f130-1618178-1558-2340-jpg_250.jpg",
                "image_width": 250,
                "image_height": 375,
                "image_bytes": 18317,
                "id": 1
            }
        ],
        "type": "message",
        "subtype": "bot_message",
        "ts": "1510187590.000189"
    },
    {
        "text": "*Nanatsu no taizai - Elizabeth Liones Cosplay by 鳗鱼霏儿*\nJapanese  -- Size: 27.05 MB (29 pages)\n<https:\/\/e-hentai.org\/g\/948766\/5e12945e3f\/>",
        "username": "e-hentai.org",
        "bot_id": "B70KX4RRS",
        "mrkdwn": true,
        "attachments": [
            {
                "fallback": "*Nanatsu no taizai - Elizabeth Liones Cosplay by 鳗鱼霏儿*\nJapanese  -- Size: 27.05 MB (29 pages)\n<https:\/\/e-hentai.org\/g\/948766\/5e12945e3f\/>",
                "image_url": "https:\/\/ehgt.org\/t\/ef\/c1\/efc130f6409b92b7b4d21e0674cca3196daea7d8-1184263-1000-1500-jpg_250.jpg",
                "image_width": 250,
                "image_height": 375,
                "image_bytes": 28512,
                "id": 1
            }
        ],
        "type": "message",
        "subtype": "bot_message",
        "ts": "1510212955.000266"
    },
    {
        "text": "*[Olivie] Elsa Granhiert Cosplay*\nJapanese  -- Size: 1.68 MB (12 pages)\n<https:\/\/e-hentai.org\/g\/942210\/3bb1084f2b\/>",
        "username": "e-hentai.org",
        "bot_id": "B70KX4RRS",
        "mrkdwn": true,
        "attachments": [
            {
                "fallback": "*[Olivie] Elsa Granhiert Cosplay*\nJapanese  -- Size: 1.68 MB (12 pages)\n<https:\/\/e-hentai.org\/g\/942210\/3bb1084f2b\/>",
                "image_url": "https:\/\/ehgt.org\/t\/a7\/1b\/a71b1683a4e750410b9031a6eb3c25dc1bc824b4-528229-1000-667-jpg_250.jpg",
                "image_width": 250,
                "image_height": 167,
                "image_bytes": 18298,
                "id": 1
            }
        ],
        "type": "message",
        "subtype": "bot_message",
        "ts": "1510213007.000051"
    },
    {
        "text": "*[雅祈] Date a live - Tokisaki Kurumi cosplay*\nJapanese  -- Size: 85.04 MB (91 pages)\n<https:\/\/e-hentai.org\/g\/959361\/48db89da6b\/>",
        "username": "e-hentai.org",
        "bot_id": "B70KX4RRS",
        "mrkdwn": true,
        "attachments": [
            {
                "fallback": "*[雅祈] Date a live - Tokisaki Kurumi cosplay*\nJapanese  -- Size: 85.04 MB (91 pages)\n<https:\/\/e-hentai.org\/g\/959361\/48db89da6b\/>",
                "image_url": "https:\/\/ehgt.org\/t\/f0\/d0\/f0d0a2f6828d62e6ac568b19480f529f85bdf53a-1555497-1528-1019-jpg_250.jpg",
                "image_width": 250,
                "image_height": 167,
                "image_bytes": 22590,
                "id": 1
            }
        ],
        "type": "message",
        "subtype": "bot_message",
        "ts": "1510213025.000233"
    },
    {
        "text": "*Nanatsu no taizai - Elizabeth Liones Cosplay by 鳗鱼霏儿*\nJapanese  -- Size: 27.05 MB (29 pages)\n<https:\/\/e-hentai.org\/g\/948766\/5e12945e3f\/>",
        "username": "e-hentai.org",
        "bot_id": "B70KX4RRS",
        "mrkdwn": true,
        "attachments": [
            {
                "fallback": "*Nanatsu no taizai - Elizabeth Liones Cosplay by 鳗鱼霏儿*\nJapanese  -- Size: 27.05 MB (29 pages)\n<https:\/\/e-hentai.org\/g\/948766\/5e12945e3f\/>",
                "image_url": "https:\/\/ehgt.org\/t\/ef\/c1\/efc130f6409b92b7b4d21e0674cca3196daea7d8-1184263-1000-1500-jpg_250.jpg",
                "image_width": 250,
                "image_height": 375,
                "image_bytes": 28512,
                "id": 1
            }
        ],
        "type": "message",
        "subtype": "bot_message",
        "ts": "1510213044.000131"
    },
    {
        "text": "*(C82) [Final Dearest (Kibashii)] Toaru Kibashi no Kanzaki Kaori (Toaru Majutsu no Index)(Complete-Hq)*\nJapanese  -- Size: 368.8 MB (574 pages)\n<https:\/\/e-hentai.org\/g\/681228\/0d06612e17\/>",
        "username": "e-hentai.org",
        "bot_id": "B70KX4RRS",
        "mrkdwn": true,
        "attachments": [
            {
                "fallback": "*(C82) [Final Dearest (Kibashii)] Toaru Kibashi no Kanzaki Kaori (Toaru Majutsu no Index)(Complete-Hq)*\nJapanese  -- Size: 368.8 MB (574 pages)\n<https:\/\/e-hentai.org\/g\/681228\/0d06612e17\/>",
                "image_url": "https:\/\/ehgt.org\/t\/78\/5f\/785f3eb2d51bbe7cd77541f95769dccc99a2fb42-410420-1700-2556-jpg_250.jpg",
                "image_width": 249,
                "image_height": 375,
                "image_bytes": 14524,
                "id": 1
            }
        ],
        "type": "message",
        "subtype": "bot_message",
        "ts": "1510213352.000035"
    },
    {
        "text": "*coser:kibashi*\nJapanese  -- Size: 10.97 MB (47 pages)\n<https:\/\/e-hentai.org\/g\/538197\/d7a9fd6dd0\/>",
        "username": "e-hentai.org",
        "bot_id": "B70KX4RRS",
        "mrkdwn": true,
        "attachments": [
            {
                "fallback": "*coser:kibashi*\nJapanese  -- Size: 10.97 MB (47 pages)\n<https:\/\/e-hentai.org\/g\/538197\/d7a9fd6dd0\/>",
                "image_url": "https:\/\/ehgt.org\/t\/79\/ea\/79ea3e8e479b67805ad4895fc7fc44e9147a5004-90321-584-878-jpg_250.jpg",
                "image_width": 249,
                "image_height": 375,
                "image_bytes": 19640,
                "id": 1
            }
        ],
        "type": "message",
        "subtype": "bot_message",
        "ts": "1510213459.000181"
    },
    {
        "text": "*(COSHOLIC 2) [FINAL DEAREST (Kibashii)] Mou-chan wa Ore no Yome! (Ikkitousen)*\nJapanese  -- Size: 110.8 MB (67 pages)\n<https:\/\/e-hentai.org\/g\/643713\/db959e5935\/>",
        "username": "e-hentai.org",
        "bot_id": "B70KX4RRS",
        "mrkdwn": true,
        "attachments": [
            {
                "fallback": "*(COSHOLIC 2) [FINAL DEAREST (Kibashii)] Mou-chan wa Ore no Yome! (Ikkitousen)*\nJapanese  -- Size: 110.8 MB (67 pages)\n<https:\/\/e-hentai.org\/g\/643713\/db959e5935\/>",
                "image_url": "https:\/\/ehgt.org\/t\/8f\/36\/8f36208b3a5ae957d4c7e29b8dbb9aad7843f130-1618178-1558-2340-jpg_250.jpg",
                "image_width": 250,
                "image_height": 375,
                "image_bytes": 18317,
                "id": 1
            }
        ],
        "type": "message",
        "subtype": "bot_message",
        "ts": "1510213474.000253"
    },
    {
        "text": "*(COSHOLIC 2) [FINAL DEAREST (Kibashii)] Mou-chan wa Ore no Yome! (Ikkitousen)*\nJapanese  -- Size: 162.1 MB (90 pages)\n<https:\/\/e-hentai.org\/g\/643715\/3f427c873b\/>",
        "username": "e-hentai.org",
        "bot_id": "B70KX4RRS",
        "mrkdwn": true,
        "attachments": [
            {
                "fallback": "*(COSHOLIC 2) [FINAL DEAREST (Kibashii)] Mou-chan wa Ore no Yome! (Ikkitousen)*\nJapanese  -- Size: 162.1 MB (90 pages)\n<https:\/\/e-hentai.org\/g\/643715\/3f427c873b\/>",
                "image_url": "https:\/\/ehgt.org\/t\/ff\/42\/ff424c7ad1699ee0da635df9ee928ae014b6c7ad-1470341-1426-2130-jpg_250.jpg",
                "image_width": 250,
                "image_height": 373,
                "image_bytes": 16507,
                "id": 1
            }
        ],
        "type": "message",
        "subtype": "bot_message",
        "ts": "1510213504.000051"
    },
    {
        "text": "*(COSHOLIC 2) [FINAL DEAREST (Kibashii)] Mou-chan wa Ore no Yome! (Ikkitousen)*\nJapanese  -- Size: 120.0 MB (66 pages)\n<https:\/\/e-hentai.org\/g\/643717\/766bea2e38\/>",
        "username": "e-hentai.org",
        "bot_id": "B70KX4RRS",
        "mrkdwn": true,
        "attachments": [
            {
                "fallback": "*(COSHOLIC 2) [FINAL DEAREST (Kibashii)] Mou-chan wa Ore no Yome! (Ikkitousen)*\nJapanese  -- Size: 120.0 MB (66 pages)\n<https:\/\/e-hentai.org\/g\/643717\/766bea2e38\/>",
                "image_url": "https:\/\/ehgt.org\/t\/b0\/7a\/b07a75c9a1f8a68530087abedfe158d01a64d5d2-1578188-1533-2304-jpg_250.jpg",
                "image_width": 250,
                "image_height": 375,
                "image_bytes": 17369,
                "id": 1
            }
        ],
        "type": "message",
        "subtype": "bot_message",
        "ts": "1510213516.000286"
    }
]